dcf/__init__.py
dcf/cli.py
dcf/device.py
dcf/lint.py
dcf/parse.py
dcf/print.py
dcf2dev/__init__.py
dcf2dev/cdevice.py
dcf2dev/cli.py
dcf2dev/data/dev.c.em
dcf2dev/data/dev.h.em
dcfgen/__init__.py
dcfgen/cli.py
dcfgen/data/master.dcf.em
dcf_tools-2.4.2.dist-info/METADATA
dcf_tools-2.4.2.dist-info/WHEEL
dcf_tools-2.4.2.dist-info/entry_points.txt
dcf_tools-2.4.2.dist-info/top_level.txt
dcf_tools-2.4.2.dist-info/RECORD
