Metadata-Version: 2.1
Name: dcf-tools
Version: 2.4.2
Summary: Tools to generate and manipulate DCF files
Author-email: "J. S. Seldenthuis" <jseldenthuis@lely.com>
Project-URL: Home Page, https://gitlab.com/lely_industries/lely-core
Classifier: License :: OSI Approved :: Apache Software License
Requires-Dist: PyYAML (>=3.08)
Requires-Dist: empy (>=3.3.2)
